pixcore/__init__.py
pixcore/brcode.py
pixcore/cli.py
pixcore/config_manager.py
pixcore/constants.py
pixcore/decipher.py
pixcore/exceptions.py
pixcore/models.py
pixcore/utils.py
pixcore/validate.py
pixcore-1.0.0.dist-info/LICENSE
pixcore-1.0.0.dist-info/METADATA
pixcore-1.0.0.dist-info/WHEEL
pixcore-1.0.0.dist-info/entry_points.txt
pixcore-1.0.0.dist-info/RECORD
