Metadata-Version: 2.3
Name: pixcore
Version: 1.0.0
Summary: Uma biblioteca Python completa para a geração de BR Codes (QR Code e Copia e Cola) do Pix, seguindo as especificações do Banco Central do Brasil.
License: MIT License
Author: Gustavo Carreiro
Author-email: gustavo.carreiro@outlook.com
Requires-Python: >=3.13,<4.0
Classifier: Development Status :: 4 - Beta
Classifier: Intended Audience :: Developers
Classifier: Intended Audience :: Financial and Insurance Industry
Classifier: Topic :: Software Development :: Libraries :: Python Modules
Classifier: Topic :: Office/Business :: Financial
Classifier: License :: OSI Approved :: MIT License
Classifier: Natural Language :: Portuguese (Brazilian)
Classifier: Operating System :: OS Independent
Classifier: Programming Language :: Python :: 3
Classifier: Programming Language :: Python :: 3.8
Classifier: Programming Language :: Python :: 3.9
Classifier: Programming Language :: Python :: 3.10
Classifier: Programming Language :: Python :: 3.11
Classifier: Programming Language :: Python :: 3.12
Classifier: Programming Language :: Python :: 3 :: Only
Requires-Dist: pillow (>=11.3.0,<12.0.0)
Requires-Dist: pyfiglet (>=1.0.4,<2.0.0)
Requires-Dist: qrcode[pil] (>=8.2,<9.0)
Requires-Dist: rich (>=14.1.0,<15.0.0)
Requires-Dist: typer (>=0.16.0,<0.17.0)
Project-URL: Bug Tracker, https://github.com/gustjose/pixcore/issues
Project-URL: Documentação, https://gustjose.github.io/pixcore/
